MANIFEST.in
setup.py
RESOURCES/.suffix
RESOURCES/dummy
efuntool/__init__.py
efuntool/bin.py
efuntool/ebooltool.py
efuntool/efuntool.py
efuntool/eobjtool.py
efuntool/etypetool.py
efuntool/proposition.py
efuntool.egg-info/PKG-INFO
efuntool.egg-info/SOURCES.txt
efuntool.egg-info/dependency_links.txt
efuntool.egg-info/entry_points.txt
efuntool.egg-info/top_level.txt