Metadata-Version: 1.1
Name: efuntool
Version: 0.0.67
Summary: handle,.in progressing..,APIs
Home-page: https://github.com/ihgazni2/efuntool
Author: ihgazni2
Author-email: UNKNOWN
License: MIT
Platform: UNKNOWN
Classifier: Environment :: Console
Classifier: Environment :: Web Environment
Classifier: Intended Audience :: End Users/Desktop
Classifier: Intended Audience :: Developers
Classifier: Intended Audience :: System Administrators
Classifier: Programming Language :: Python
